rogue/__init__.py
rogue/__main__.py
rogue/errors.py
rogue/backends/__init__.py
rogue/backends/base.py
rogue/backends/errors.py
rogue/backends/sqlite/__init__.py
rogue/backends/sqlite/client.py
rogue/backends/sqlite/query.py
rogue/backends/sqlite/schema.py
rogue/managers/__init__.py
rogue/managers/base.py
rogue/managers/errors.py
rogue/migrations/__init__.py
rogue/migrations/base.py
rogue/models/__init__.py
rogue/models/base.py
rogue/models/errors.py
rogue/models/fields.py
rogue/models/utils.py
rogue/query/__init__.py
rogue/query/descriptors.py
rogue/query/query.py
rogue/settings/__init__.py
rogue/settings/default_settings.py
RogueORM-0.1.0.dist-info/LICENSE
RogueORM-0.1.0.dist-info/METADATA
RogueORM-0.1.0.dist-info/WHEEL
RogueORM-0.1.0.dist-info/top_level.txt
RogueORM-0.1.0.dist-info/RECORD
