Metadata-Version: 2.1
Name: RogueORM
Version: 0.1.0
Summary: An ORM that strives to eradicate N+1 issues.
Author-email: Maxime Toussaint <m.toussaint@mail.com>
License: MIT License
Project-URL: Homepage, https://github.com/MaxDude132/RogueORM
Keywords: orm,database
Classifier: License :: OSI Approved :: MIT License
Classifier: Programming Language :: Python
Classifier: Programming Language :: Python :: 3
Requires-Python: >=3.10
License-File: LICENSE
Requires-Dist: python-dotenv
Requires-Dist: sqlparse
Provides-Extra: dev
Requires-Dist: black ; extra == 'dev'
Requires-Dist: bumpver ; extra == 'dev'
Requires-Dist: isort ; extra == 'dev'
Requires-Dist: pip-tools ; extra == 'dev'
Requires-Dist: pytest ; extra == 'dev'
